<?xml version="1.0" encoding="utf-8" standalone="yes"?>
<channel>
	<id>documentalesatonline2</id>
	<name>La Guarida de bizzente</name>
	<language>es</language>
	<update_url></update_url>
	<active>false</active>
	<include_in_global_search>disabled</include_in_global_search>
	
	<version>1</version>
	<adult>false</adult>
	<date>01/07/2016</date>
	<changes>Eliminado código innecesario.</changes>
	<fanart></fanart>
	<thumbnail></thumbnail>
	<categories>
		<category>documentary</category>
	</categories>
</channel>
